Metadata-Version: 1.1
Name: CIpipe
Version: 1.148
Summary: CRISPR Indel pipe
Home-page: https://zlab.umassmed.edu/CIpipe/
Author: Yingxiang Li
Author-email: xlccalyx@gmail.com
License: GPLv3
Download-URL: https://pypi.python.org/pypi/CIpipe
Keywords: CRISPR Indel pipe
Platform: UNKNOWN
Classifier: Development Status :: 3 - Alpha
Classifier: Intended Audience :: Developers
Classifier: Topic :: Software Development :: Build Tools
Classifier: License :: OSI Approved :: GNU General Public License v3 (GPLv3)
Classifier: Programming Language :: Python :: 2.7
